joyous_departures/__init__.py
joyous_departures/corpus.py
joyous_departures-2.0.1.dist-info/METADATA
joyous_departures-2.0.1.dist-info/WHEEL
joyous_departures-2.0.1.dist-info/RECORD
